snipper/__init__.py
snipper/api.py
snipper/completers.py
snipper/repo.py
snipper/snipper.py
snipper/snippet.py
snipper/utils.py
snipper-1.4.0.dist-info/LICENSE.txt
snipper-1.4.0.dist-info/METADATA
snipper-1.4.0.dist-info/WHEEL
snipper-1.4.0.dist-info/entry_points.txt
snipper-1.4.0.dist-info/top_level.txt
snipper-1.4.0.dist-info/RECORD
