Metadata-Version: 2.1
Name: snipper
Version: 1.4.0
Summary: A command-line tool to manage Bitbucket snippets.
Home-page: https://github.com/mesuutt/snipper
Author: Mesut Tasci
Author-email: mst.tasci@gmail.com
License: MIT
Keywords: bitbucket snippet gist command-line cli
Platform: UNKNOWN
Classifier: Environment :: Console
Classifier: License :: OSI Approved :: MIT License
Classifier: Development Status :: 4 - Beta
Classifier: Programming Language :: Python
Classifier: Programming Language :: Python :: 2.6
Classifier: Programming Language :: Python :: 2.7
Classifier: Programming Language :: Python :: 3
Classifier: Programming Language :: Python :: 3.4
Classifier: Programming Language :: Python :: 3.5
Classifier: Programming Language :: Python :: 3.6
Classifier: Intended Audience :: Developers
Classifier: Operating System :: POSIX
Classifier: Operating System :: MacOS :: MacOS X
Requires-Dist: requests (>=2.12)
Requires-Dist: click (>=6.7)
Requires-Dist: prompt-toolkit (>=1.0)
Requires-Dist: pyperclip (>=1.5)
